LICENSE
MANIFEST.in
README.md
requirements.txt
setup.py
safe/__init__.py
safe/safe.cpp
safe/safe.py
safe/safe_calc.pyx
sga_safe.egg-info/PKG-INFO
sga_safe.egg-info/SOURCES.txt
sga_safe.egg-info/dependency_links.txt
sga_safe.egg-info/requires.txt
sga_safe.egg-info/top_level.txt
tests/__init__.py
tests/context.py
tests/test_basic.py