Metadata-Version: 2.1
Name: sga-safe
Version: 0.1.1
Summary: SAFE implementation for Python
Home-page: https://github.com/usajusaj/safe
Author: Matej Usaj
Author-email: usaj.m@utoronto.ca
License: MIT
Platform: UNKNOWN
Classifier: Programming Language :: Python :: 3
Classifier: License :: OSI Approved :: MIT License
